{
  "HConRes14": {
    "event_count": 0,
    "first_seen": "2025-10-24T05:32:17.656665",
    "last_seen": "2025-11-18T04:09:42.746931",
    "occurrence_count": 26,
    "path": "country:us/state:usa/sessions/119/bills/HConRes14",
    "session": "119",
    "vote_count": 2
  },
  "HJRes104": {
    "event_count": 0,
    "first_seen": "2025-10-24T05:32:17.656665",
    "last_seen": "2025-11-18T04:09:42.746931",
    "occurrence_count": 26,
    "path": "country:us/state:usa/sessions/119/bills/HJRes104",
    "session": "119",
    "vote_count": 2
  },
  "HJRes105": {
    "event_count": 0,
    "first_seen": "2025-10-24T05:32:17.656665",
    "last_seen": "2025-11-18T04:09:42.746931",
    "occurrence_count": 26,
    "path": "country:us/state:usa/sessions/119/bills/HJRes105",
    "session": "119",
    "vote_count": 2
  },
  "HJRes106": {
    "event_count": 0,
    "first_seen": "2025-10-24T05:32:17.656665",
    "last_seen": "2025-11-18T04:09:42.746931",
    "occurrence_count": 26,
    "path": "country:us/state:usa/sessions/119/bills/HJRes106",
    "session": "119",
    "vote_count": 2
  },
  "HJRes20": {
    "event_count": 0,
    "first_seen": "2025-10-24T05:32:17.656665",
    "last_seen": "2025-11-18T04:09:42.746931",
    "occurrence_count": 26,
    "path": "country:us/state:usa/sessions/119/bills/HJRes20",
    "session": "119",
    "vote_count": 2
  },
  "HJRes24": {
    "event_count": 0,
    "first_seen": "2025-10-24T05:32:17.656665",
    "last_seen": "2025-11-18T04:09:42.746931",
    "occurrence_count": 26,
    "path": "country:us/state:usa/sessions/119/bills/HJRes24",
    "session": "119",
    "vote_count": 2
  },
  "HJRes25": {
    "event_count": 0,
    "first_seen": "2025-10-24T05:32:17.656665",
    "last_seen": "2025-11-18T04:09:42.746931",
    "occurrence_count": 26,
    "path": "country:us/state:usa/sessions/119/bills/HJRes25",
    "session": "119",
    "vote_count": 2
  },
  "HJRes35": {
    "event_count": 0,
    "first_seen": "2025-10-24T05:32:17.656665",
    "last_seen": "2025-11-18T04:09:42.746931",
    "occurrence_count": 26,
    "path": "country:us/state:usa/sessions/119/bills/HJRes35",
    "session": "119",
    "vote_count": 1
  },
  "HJRes42": {
    "event_count": 0,
    "first_seen": "2025-10-24T05:32:17.656665",
    "last_seen": "2025-11-18T04:09:42.746931",
    "occurrence_count": 26,
    "path": "country:us/state:usa/sessions/119/bills/HJRes42",
    "session": "119",
    "vote_count": 2
  },
  "HJRes60": {
    "event_count": 0,
    "first_seen": "2025-10-24T05:32:17.656665",
    "last_seen": "2025-11-18T04:09:42.746931",
    "occurrence_count": 26,
    "path": "country:us/state:usa/sessions/119/bills/HJRes60",
    "session": "119",
    "vote_count": 2
  },
  "HJRes61": {
    "event_count": 0,
    "first_seen": "2025-10-24T05:32:17.656665",
    "last_seen": "2025-11-18T04:09:42.746931",
    "occurrence_count": 26,
    "path": "country:us/state:usa/sessions/119/bills/HJRes61",
    "session": "119",
    "vote_count": 2
  },
  "HJRes75": {
    "event_count": 0,
    "first_seen": "2025-10-24T05:32:17.656665",
    "last_seen": "2025-11-18T04:09:42.746931",
    "occurrence_count": 26,
    "path": "country:us/state:usa/sessions/119/bills/HJRes75",
    "session": "119",
    "vote_count": 2
  },
  "HJRes87": {
    "event_count": 0,
    "first_seen": "2025-10-24T05:32:17.656665",
    "last_seen": "2025-11-18T04:09:42.746931",
    "occurrence_count": 26,
    "path": "country:us/state:usa/sessions/119/bills/HJRes87",
    "session": "119",
    "vote_count": 2
  },
  "HJRes88": {
    "event_count": 0,
    "first_seen": "2025-10-24T05:32:17.656665",
    "last_seen": "2025-11-18T04:09:42.746931",
    "occurrence_count": 26,
    "path": "country:us/state:usa/sessions/119/bills/HJRes88",
    "session": "119",
    "vote_count": 2
  },
  "HJRes89": {
    "event_count": 0,
    "first_seen": "2025-10-24T05:32:17.656665",
    "last_seen": "2025-11-18T04:09:42.746931",
    "occurrence_count": 26,
    "path": "country:us/state:usa/sessions/119/bills/HJRes89",
    "session": "119",
    "vote_count": 2
  },
  "SConRes22": {
    "event_count": 0,
    "first_seen": "2025-10-24T05:32:17.656665",
    "last_seen": "2025-11-18T04:09:42.746931",
    "occurrence_count": 26,
    "path": "country:us/state:usa/sessions/119/bills/SConRes22",
    "session": "119",
    "vote_count": 1
  },
  "SConRes7": {
    "event_count": 0,
    "first_seen": "2025-10-24T05:32:17.656665",
    "last_seen": "2025-11-18T04:09:42.746931",
    "occurrence_count": 26,
    "path": "country:us/state:usa/sessions/119/bills/SConRes7",
    "session": "119",
    "vote_count": 2
  },
  "SJRes10": {
    "event_count": 0,
    "first_seen": "2025-10-24T05:32:17.656665",
    "last_seen": "2025-11-18T04:09:42.746931",
    "occurrence_count": 26,
    "path": "country:us/state:usa/sessions/119/bills/SJRes10",
    "session": "119",
    "vote_count": 1
  },
  "SJRes11": {
    "event_count": 0,
    "first_seen": "2025-10-24T05:32:17.656665",
    "last_seen": "2025-11-18T04:09:42.746931",
    "occurrence_count": 26,
    "path": "country:us/state:usa/sessions/119/bills/SJRes11",
    "session": "119",
    "vote_count": 2
  },
  "SJRes12": {
    "event_count": 0,
    "first_seen": "2025-10-24T05:32:17.656665",
    "last_seen": "2025-11-18T04:09:42.746931",
    "occurrence_count": 26,
    "path": "country:us/state:usa/sessions/119/bills/SJRes12",
    "session": "119",
    "vote_count": 1
  },
  "SJRes13": {
    "event_count": 0,
    "first_seen": "2025-10-24T05:32:17.656665",
    "last_seen": "2025-11-18T04:09:42.746931",
    "occurrence_count": 26,
    "path": "country:us/state:usa/sessions/119/bills/SJRes13",
    "session": "119",
    "vote_count": 2
  },
  "SJRes18": {
    "event_count": 0,
    "first_seen": "2025-10-24T05:32:17.656665",
    "last_seen": "2025-11-18T04:09:42.746931",
    "occurrence_count": 26,
    "path": "country:us/state:usa/sessions/119/bills/SJRes18",
    "session": "119",
    "vote_count": 2
  },
  "SJRes26": {
    "event_count": 0,
    "first_seen": "2025-10-24T05:32:17.656665",
    "last_seen": "2025-11-18T04:09:42.746931",
    "occurrence_count": 26,
    "path": "country:us/state:usa/sessions/119/bills/SJRes26",
    "session": "119",
    "vote_count": 1
  },
  "SJRes28": {
    "event_count": 0,
    "first_seen": "2025-10-24T05:32:17.656665",
    "last_seen": "2025-11-18T04:09:42.746931",
    "occurrence_count": 26,
    "path": "country:us/state:usa/sessions/119/bills/SJRes28",
    "session": "119",
    "vote_count": 2
  },
  "SJRes3": {
    "event_count": 0,
    "first_seen": "2025-10-24T05:32:17.656665",
    "last_seen": "2025-11-18T04:09:42.746931",
    "occurrence_count": 26,
    "path": "country:us/state:usa/sessions/119/bills/SJRes3",
    "session": "119",
    "vote_count": 2
  },
  "SJRes31": {
    "event_count": 0,
    "first_seen": "2025-10-24T05:32:17.656665",
    "last_seen": "2025-11-18T04:09:42.746931",
    "occurrence_count": 26,
    "path": "country:us/state:usa/sessions/119/bills/SJRes31",
    "session": "119",
    "vote_count": 2
  },
  "SJRes33": {
    "event_count": 0,
    "first_seen": "2025-10-24T05:32:17.656665",
    "last_seen": "2025-11-18T04:09:42.746931",
    "occurrence_count": 26,
    "path": "country:us/state:usa/sessions/119/bills/SJRes33",
    "session": "119",
    "vote_count": 1
  },
  "SJRes34": {
    "event_count": 0,
    "first_seen": "2025-10-24T05:32:17.656665",
    "last_seen": "2025-11-18T04:09:42.746931",
    "occurrence_count": 26,
    "path": "country:us/state:usa/sessions/119/bills/SJRes34",
    "session": "119",
    "vote_count": 1
  },
  "SJRes37": {
    "event_count": 0,
    "first_seen": "2025-10-24T05:32:17.656665",
    "last_seen": "2025-11-18T04:09:42.746931",
    "occurrence_count": 26,
    "path": "country:us/state:usa/sessions/119/bills/SJRes37",
    "session": "119",
    "vote_count": 1
  },
  "SJRes41": {
    "event_count": 0,
    "first_seen": "2025-10-24T05:32:17.656665",
    "last_seen": "2025-11-18T04:09:42.746931",
    "occurrence_count": 26,
    "path": "country:us/state:usa/sessions/119/bills/SJRes41",
    "session": "119",
    "vote_count": 1
  },
  "SJRes49": {
    "event_count": 0,
    "first_seen": "2025-10-24T05:32:17.656665",
    "last_seen": "2025-11-18T04:09:42.746931",
    "occurrence_count": 26,
    "path": "country:us/state:usa/sessions/119/bills/SJRes49",
    "session": "119",
    "vote_count": 1
  },
  "SJRes53": {
    "event_count": 0,
    "first_seen": "2025-10-24T05:32:17.656665",
    "last_seen": "2025-11-18T04:09:42.746931",
    "occurrence_count": 26,
    "path": "country:us/state:usa/sessions/119/bills/SJRes53",
    "session": "119",
    "vote_count": 1
  },
  "SJRes54": {
    "event_count": 0,
    "first_seen": "2025-10-24T05:32:17.656665",
    "last_seen": "2025-11-18T04:09:42.746931",
    "occurrence_count": 26,
    "path": "country:us/state:usa/sessions/119/bills/SJRes54",
    "session": "119",
    "vote_count": 1
  },
  "SJRes55": {
    "event_count": 0,
    "first_seen": "2025-10-24T05:32:17.656665",
    "last_seen": "2025-11-18T04:09:42.746931",
    "occurrence_count": 26,
    "path": "country:us/state:usa/sessions/119/bills/SJRes55",
    "session": "119",
    "vote_count": 6
  },
  "SJRes59": {
    "event_count": 0,
    "first_seen": "2025-10-24T05:32:17.656665",
    "last_seen": "2025-11-18T04:09:42.746931",
    "occurrence_count": 26,
    "path": "country:us/state:usa/sessions/119/bills/SJRes59",
    "session": "119",
    "vote_count": 1
  },
  "SJRes60": {
    "event_count": 0,
    "first_seen": "2025-10-24T05:32:17.656665",
    "last_seen": "2025-11-18T04:09:42.746931",
    "occurrence_count": 26,
    "path": "country:us/state:usa/sessions/119/bills/SJRes60",
    "session": "119",
    "vote_count": 1
  },
  "SJRes7": {
    "event_count": 0,
    "first_seen": "2025-10-24T05:32:17.656665",
    "last_seen": "2025-11-18T04:09:42.746931",
    "occurrence_count": 26,
    "path": "country:us/state:usa/sessions/119/bills/SJRes7",
    "session": "119",
    "vote_count": 2
  },
  "SJRes71": {
    "event_count": 0,
    "first_seen": "2025-10-24T05:32:17.656665",
    "last_seen": "2025-11-18T04:09:42.746931",
    "occurrence_count": 26,
    "path": "country:us/state:usa/sessions/119/bills/SJRes71",
    "session": "119",
    "vote_count": 1
  },
  "SJRes83": {
    "event_count": 0,
    "first_seen": "2025-10-24T05:32:17.656665",
    "last_seen": "2025-11-18T04:09:42.746931",
    "occurrence_count": 26,
    "path": "country:us/state:usa/sessions/119/bills/SJRes83",
    "session": "119",
    "vote_count": 1
  },
  "SRes195": {
    "event_count": 0,
    "first_seen": "2025-10-24T05:32:17.656665",
    "last_seen": "2025-11-18T04:09:42.746931",
    "occurrence_count": 26,
    "path": "country:us/state:usa/sessions/119/bills/SRes195",
    "session": "119",
    "vote_count": 1
  },
  "SRes377": {
    "event_count": 0,
    "first_seen": "2025-10-24T05:32:17.656665",
    "last_seen": "2025-11-18T04:09:42.746931",
    "occurrence_count": 26,
    "path": "country:us/state:usa/sessions/119/bills/SRes377",
    "session": "119",
    "vote_count": 6
  },
  "SRes412": {
    "event_count": 0,
    "first_seen": "2025-10-24T05:32:17.656665",
    "last_seen": "2025-11-18T04:09:42.746931",
    "occurrence_count": 26,
    "path": "country:us/state:usa/sessions/119/bills/SRes412",
    "session": "119",
    "vote_count": 2
  }
}