{
  "legislative_session": "2025-2026",
  "identifier": "H 107",
  "title": "An act relating to reports or complaints of sex offenses or sexual harassment",
  "from_organization": "~{\"classification\": \"lower\"}",
  "classification": [
    "bill"
  ],
  "subject": [],
  "abstracts": [],
  "other_titles": [],
  "other_identifiers": [],
  "actions": [
    {
      "description": "Read first time and referred to the Committee on Judiciary",
      "date": "2025-01-28",
      "organization_id": "~{\"classification\": \"lower\"}",
      "classification": [
        "introduction"
      ],
      "related_entities": [],
      "_processing": {
        "log_file_created": "2025-11-26T05:54:34Z"
      }
    }
  ],
  "sponsorships": [
    {
      "name": "Troy Headrick",
      "classification": "primary",
      "entity_type": "person",
      "primary": true,
      "person_id": "~{\"chamber\": \"lower\", \"name\": \"Troy Headrick\"}",
      "organization_id": null
    },
    {
      "name": "Mollie Burke",
      "classification": "cosponsor",
      "entity_type": "person",
      "primary": false,
      "person_id": "~{\"chamber\": \"lower\", \"name\": \"Mollie Burke\"}",
      "organization_id": null
    },
    {
      "name": "Voranus Coffin IV",
      "classification": "cosponsor",
      "entity_type": "person",
      "primary": false,
      "person_id": "~{\"chamber\": \"lower\", \"name\": \"Voranus Coffin IV\"}",
      "organization_id": null
    },
    {
      "name": "Kate Logan",
      "classification": "cosponsor",
      "entity_type": "person",
      "primary": false,
      "person_id": "~{\"chamber\": \"lower\", \"name\": \"Kate Logan\"}",
      "organization_id": null
    },
    {
      "name": "Kate McCann",
      "classification": "cosponsor",
      "entity_type": "person",
      "primary": false,
      "person_id": "~{\"chamber\": \"lower\", \"name\": \"Kate McCann\"}",
      "organization_id": null
    },
    {
      "name": "Phil Pouech",
      "classification": "cosponsor",
      "entity_type": "person",
      "primary": false,
      "person_id": "~{\"chamber\": \"lower\", \"name\": \"Phil Pouech\"}",
      "organization_id": null
    },
    {
      "name": "Monique Priestley",
      "classification": "cosponsor",
      "entity_type": "person",
      "primary": false,
      "person_id": "~{\"chamber\": \"lower\", \"name\": \"Monique Priestley\"}",
      "organization_id": null
    },
    {
      "name": "Kirk White",
      "classification": "cosponsor",
      "entity_type": "person",
      "primary": false,
      "person_id": "~{\"chamber\": \"lower\", \"name\": \"Kirk White\"}",
      "organization_id": null
    }
  ],
  "related_bills": [],
  "versions": [
    {
      "note": "As Introduced",
      "links": [
        {
          "url": "https://legislature.vermont.gov/Documents/2026/Docs/BILLS/H-0107/H-0107%20As%20Introduced.pdf",
          "media_type": "application/pdf"
        }
      ],
      "date": "",
      "classification": ""
    }
  ],
  "documents": [
    {
      "note": "Witness List",
      "links": [
        {
          "url": "https://legislature.vermont.gov/bill/print/2026/H107/witnesses",
          "media_type": "text/html"
        }
      ],
      "date": "",
      "classification": ""
    },
    {
      "note": "Committee Meetings",
      "links": [
        {
          "url": "https://legislature.vermont.gov/bill/print/2026/H107/meetings",
          "media_type": "text/html"
        }
      ],
      "date": "",
      "classification": ""
    }
  ],
  "citations": [],
  "sources": [
    {
      "url": "http://legislature.vermont.gov/bill/loadBillsIntroduced/2026/",
      "note": ""
    },
    {
      "url": "http://legislature.vermont.gov/bill/status/2026/H.107",
      "note": ""
    },
    {
      "url": "http://legislature.vermont.gov/bill/loadBillDetailedStatus/2026/243",
      "note": ""
    },
    {
      "url": "http://legislature.vermont.gov/bill/loadBillRollCalls/2026/243",
      "note": ""
    }
  ],
  "extras": {},
  "jurisdiction": {
    "id": "ocd-jurisdiction/country:us/state:vt/government",
    "name": "Vermont",
    "classification": "state",
    "division_id": "ocd-division/country:us/state:vt"
  },
  "_processing": {
    "logs_latest_update": "2025-11-26T05:54:35Z"
  }
}