{
  "legislative_session": "2025-2026",
  "identifier": "H 283",
  "title": "An act relating to delegation of authority to regulate use of State waters",
  "from_organization": "~{\"classification\": \"lower\"}",
  "classification": [
    "bill"
  ],
  "subject": [],
  "abstracts": [],
  "other_titles": [],
  "other_identifiers": [],
  "actions": [
    {
      "description": "Read first time and referred to the Committee on Environment",
      "date": "2025-02-19",
      "organization_id": "~{\"classification\": \"lower\"}",
      "classification": [
        "introduction"
      ],
      "related_entities": [],
      "_processing": {
        "log_file_created": "2025-11-26T05:54:33Z"
      }
    }
  ],
  "sponsorships": [
    {
      "name": "Leanne Harple",
      "classification": "primary",
      "entity_type": "person",
      "primary": true,
      "person_id": "~{\"chamber\": \"lower\", \"name\": \"Leanne Harple\"}",
      "organization_id": null
    },
    {
      "name": "Monique Priestley",
      "classification": "primary",
      "entity_type": "person",
      "primary": true,
      "person_id": "~{\"chamber\": \"lower\", \"name\": \"Monique Priestley\"}",
      "organization_id": null
    },
    {
      "name": "Mollie Burke",
      "classification": "cosponsor",
      "entity_type": "person",
      "primary": false,
      "person_id": "~{\"chamber\": \"lower\", \"name\": \"Mollie Burke\"}",
      "organization_id": null
    },
    {
      "name": "Bridget Burkhardt",
      "classification": "cosponsor",
      "entity_type": "person",
      "primary": false,
      "person_id": "~{\"chamber\": \"lower\", \"name\": \"Bridget Burkhardt\"}",
      "organization_id": null
    },
    {
      "name": "R. Scott Campbell",
      "classification": "cosponsor",
      "entity_type": "person",
      "primary": false,
      "person_id": "~{\"chamber\": \"lower\", \"name\": \"R. Scott Campbell\"}",
      "organization_id": null
    },
    {
      "name": "Leonora Dodge",
      "classification": "cosponsor",
      "entity_type": "person",
      "primary": false,
      "person_id": "~{\"chamber\": \"lower\", \"name\": \"Leonora Dodge\"}",
      "organization_id": null
    },
    {
      "name": "Robert Hunter",
      "classification": "cosponsor",
      "entity_type": "person",
      "primary": false,
      "person_id": "~{\"chamber\": \"lower\", \"name\": \"Robert Hunter\"}",
      "organization_id": null
    },
    {
      "name": "Larry Labor",
      "classification": "cosponsor",
      "entity_type": "person",
      "primary": false,
      "person_id": "~{\"chamber\": \"lower\", \"name\": \"Larry Labor\"}",
      "organization_id": null
    },
    {
      "name": "Kate Lalley",
      "classification": "cosponsor",
      "entity_type": "person",
      "primary": false,
      "person_id": "~{\"chamber\": \"lower\", \"name\": \"Kate Lalley\"}",
      "organization_id": null
    },
    {
      "name": "James Masland",
      "classification": "cosponsor",
      "entity_type": "person",
      "primary": false,
      "person_id": "~{\"chamber\": \"lower\", \"name\": \"James Masland\"}",
      "organization_id": null
    },
    {
      "name": "Kate McCann",
      "classification": "cosponsor",
      "entity_type": "person",
      "primary": false,
      "person_id": "~{\"chamber\": \"lower\", \"name\": \"Kate McCann\"}",
      "organization_id": null
    },
    {
      "name": "Richard Nelson",
      "classification": "cosponsor",
      "entity_type": "person",
      "primary": false,
      "person_id": "~{\"chamber\": \"lower\", \"name\": \"Richard Nelson\"}",
      "organization_id": null
    },
    {
      "name": "Kate Nugent",
      "classification": "cosponsor",
      "entity_type": "person",
      "primary": false,
      "person_id": "~{\"chamber\": \"lower\", \"name\": \"Kate Nugent\"}",
      "organization_id": null
    },
    {
      "name": "Herb Olson",
      "classification": "cosponsor",
      "entity_type": "person",
      "primary": false,
      "person_id": "~{\"chamber\": \"lower\", \"name\": \"Herb Olson\"}",
      "organization_id": null
    },
    {
      "name": "Phil Pouech",
      "classification": "cosponsor",
      "entity_type": "person",
      "primary": false,
      "person_id": "~{\"chamber\": \"lower\", \"name\": \"Phil Pouech\"}",
      "organization_id": null
    },
    {
      "name": "Michael Southworth",
      "classification": "cosponsor",
      "entity_type": "person",
      "primary": false,
      "person_id": "~{\"chamber\": \"lower\", \"name\": \"Michael Southworth\"}",
      "organization_id": null
    },
    {
      "name": "Kenneth Wells",
      "classification": "cosponsor",
      "entity_type": "person",
      "primary": false,
      "person_id": "~{\"chamber\": \"lower\", \"name\": \"Kenneth Wells\"}",
      "organization_id": null
    }
  ],
  "related_bills": [],
  "versions": [
    {
      "note": "As Introduced",
      "links": [
        {
          "url": "https://legislature.vermont.gov/Documents/2026/Docs/BILLS/H-0283/H-0283%20As%20Introduced.pdf",
          "media_type": "application/pdf"
        }
      ],
      "date": "",
      "classification": ""
    }
  ],
  "documents": [
    {
      "note": "Witness List",
      "links": [
        {
          "url": "https://legislature.vermont.gov/bill/print/2026/H283/witnesses",
          "media_type": "text/html"
        }
      ],
      "date": "",
      "classification": ""
    },
    {
      "note": "Committee Meetings",
      "links": [
        {
          "url": "https://legislature.vermont.gov/bill/print/2026/H283/meetings",
          "media_type": "text/html"
        }
      ],
      "date": "",
      "classification": ""
    }
  ],
  "citations": [],
  "sources": [
    {
      "url": "http://legislature.vermont.gov/bill/loadBillsIntroduced/2026/",
      "note": ""
    },
    {
      "url": "http://legislature.vermont.gov/bill/status/2026/H.283",
      "note": ""
    },
    {
      "url": "http://legislature.vermont.gov/bill/loadBillDetailedStatus/2026/702",
      "note": ""
    },
    {
      "url": "http://legislature.vermont.gov/bill/loadBillRollCalls/2026/702",
      "note": ""
    }
  ],
  "extras": {},
  "jurisdiction": {
    "id": "ocd-jurisdiction/country:us/state:vt/government",
    "name": "Vermont",
    "classification": "state",
    "division_id": "ocd-division/country:us/state:vt"
  },
  "_processing": {
    "logs_latest_update": "2025-11-26T05:54:35Z"
  }
}