{"identifier": "", "motion_text": "S05 - Agriculture:Do Pass Failed 2-3-0-0-0", "motion_classification": [], "start_date": "2025-02-04T20:13:16+00:00", "result": "fail", "organization": "~{\"classification\": \"upper\"}", "legislative_session": "2025", "bill": "a0fc1526-c5b0-11f0-917d-aeaef7ee5433", "bill_action": null, "bill_identifier": "SF0192", "votes": [{"option": "yes", "voter_name": "CRAGO", "voter_id": "~{\"name\": \"CRAGO\"}", "note": ""}, {"option": "yes", "voter_name": "TALIAFERRO PEARSON", "voter_id": "~{\"name\": \"TALIAFERRO PEARSON\"}", "note": ""}, {"option": "no", "voter_name": "IDE", "voter_id": "~{\"name\": \"IDE\"}", "note": ""}, {"option": "no", "voter_name": "MCKEOWN", "voter_id": "~{\"name\": \"MCKEOWN\"}", "note": ""}, {"option": "no", "voter_name": "FRENCH", "voter_id": "~{\"name\": \"FRENCH\"}", "note": ""}], "counts": [{"option": "yes", "value": 2}, {"option": "no", "value": 3}, {"option": "absent", "value": 0}, {"option": "excused", "value": 0}, {"option": "other", "value": 0}], "sources": [{"url": "https://lso.wyoleg.gov/Legislation/2025/SF0192", "note": ""}], "extras": {}, "_id": "a0fc37d6-c5b0-11f0-917d-aeaef7ee5433"}