{
  "legislative_session": "2025-2026",
  "identifier": "S 51",
  "title": "An act relating to Vermont income tax exclusions and tax credits",
  "from_organization": "~{\"classification\": \"upper\"}",
  "classification": [
    "bill"
  ],
  "subject": [],
  "abstracts": [],
  "other_titles": [],
  "other_identifiers": [],
  "actions": [
    {
      "description": "Read 1st time & referred to Committee on Finance",
      "date": "2025-02-06",
      "organization_id": "~{\"classification\": \"upper\"}",
      "classification": [
        "introduction"
      ],
      "related_entities": [],
      "_processing": {
        "log_file_created": "2025-11-26T05:54:34Z"
      }
    },
    {
      "description": "Entered on Notice Calendar",
      "date": "2025-03-18",
      "organization_id": "~{\"classification\": \"upper\"}",
      "classification": [],
      "related_entities": [],
      "_processing": {
        "log_file_created": "2025-11-26T05:54:34Z"
      }
    },
    {
      "description": "Second Reading",
      "date": "2025-03-18",
      "organization_id": "~{\"classification\": \"upper\"}",
      "classification": [
        "reading-2"
      ],
      "related_entities": [],
      "_processing": {
        "log_file_created": "2025-11-26T05:54:34Z"
      }
    },
    {
      "description": "Favorable report with recommendation of amendment by Committee on Finance",
      "date": "2025-03-18",
      "organization_id": "~{\"classification\": \"upper\"}",
      "classification": [
        "committee-passage"
      ],
      "related_entities": [],
      "_processing": {
        "log_file_created": "2025-11-26T05:54:34Z"
      }
    },
    {
      "description": "New Business/Second Reading",
      "date": "2025-03-19",
      "organization_id": "~{\"classification\": \"upper\"}",
      "classification": [
        "reading-2"
      ],
      "related_entities": [],
      "_processing": {
        "log_file_created": "2025-11-26T05:54:34Z"
      }
    },
    {
      "description": "Favorable report with recommendation of amendment by Committee on Finance",
      "date": "2025-03-19",
      "organization_id": "~{\"classification\": \"upper\"}",
      "classification": [
        "committee-passage"
      ],
      "related_entities": [],
      "_processing": {
        "log_file_created": "2025-11-26T05:54:34Z"
      }
    },
    {
      "description": "Read 2nd time, reported favorably with recommendation of amendment by Senator Hardy for Committee on Finance",
      "date": "2025-03-19",
      "organization_id": "~{\"classification\": \"upper\"}",
      "classification": [
        "committee-passage-favorable",
        "reading-2"
      ],
      "related_entities": [],
      "_processing": {
        "log_file_created": "2025-11-26T05:54:34Z"
      }
    },
    {
      "description": "Recommendation of amendment by Committee on Finance agreed to",
      "date": "2025-03-19",
      "organization_id": "~{\"classification\": \"upper\"}",
      "classification": [],
      "related_entities": [],
      "_processing": {
        "log_file_created": "2025-11-26T05:54:34Z"
      }
    },
    {
      "description": "3rd reading ordered",
      "date": "2025-03-19",
      "organization_id": "~{\"classification\": \"upper\"}",
      "classification": [],
      "related_entities": [],
      "_processing": {
        "log_file_created": "2025-11-26T05:54:34Z"
      }
    },
    {
      "description": "New Business/Third Reading",
      "date": "2025-03-20",
      "organization_id": "~{\"classification\": \"upper\"}",
      "classification": [
        "reading-3"
      ],
      "related_entities": [],
      "_processing": {
        "log_file_created": "2025-11-26T05:54:34Z"
      }
    },
    {
      "description": "Read 3rd time & passed",
      "date": "2025-03-20",
      "organization_id": "~{\"classification\": \"upper\"}",
      "classification": [
        "reading-3"
      ],
      "related_entities": [],
      "_processing": {
        "log_file_created": "2025-11-26T05:54:34Z"
      }
    },
    {
      "description": "Read first time and referred to the Committee on Ways and Means",
      "date": "2025-03-25",
      "organization_id": "~{\"classification\": \"lower\"}",
      "classification": [
        "introduction"
      ],
      "related_entities": [],
      "_processing": {
        "log_file_created": "2025-11-26T05:54:34Z"
      }
    },
    {
      "description": "Notice Calendar: Favorable with Amendment",
      "date": "2025-05-02",
      "organization_id": "~{\"classification\": \"lower\"}",
      "classification": [],
      "related_entities": [],
      "_processing": {
        "log_file_created": "2025-11-26T05:54:34Z"
      }
    },
    {
      "description": "Action Calendar: Favorable with Amendment",
      "date": "2025-05-06",
      "organization_id": "~{\"classification\": \"lower\"}",
      "classification": [],
      "related_entities": [],
      "_processing": {
        "log_file_created": "2025-11-26T05:54:34Z"
      }
    },
    {
      "description": "Read second time",
      "date": "2025-05-06",
      "organization_id": "~{\"classification\": \"lower\"}",
      "classification": [
        "reading-2"
      ],
      "related_entities": [],
      "_processing": {
        "log_file_created": "2025-11-26T05:54:34Z"
      }
    },
    {
      "description": "Rep. Kimbell of Woodstock reported for the Committee on Ways and Means",
      "date": "2025-05-06",
      "organization_id": "~{\"classification\": \"lower\"}",
      "classification": [],
      "related_entities": [],
      "_processing": {
        "log_file_created": "2025-11-26T05:54:34Z"
      }
    },
    {
      "description": "Rep. Canfield of Fair Haven demanded yeas and nays",
      "date": "2025-05-06",
      "organization_id": "~{\"classification\": \"lower\"}",
      "classification": [],
      "related_entities": [],
      "_processing": {
        "log_file_created": "2025-11-26T05:54:34Z"
      }
    },
    {
      "description": "Report of Committee on Ways and Means agreed to",
      "date": "2025-05-06",
      "organization_id": "~{\"classification\": \"lower\"}",
      "classification": [],
      "related_entities": [],
      "_processing": {
        "log_file_created": "2025-11-26T05:54:34Z"
      }
    },
    {
      "description": "Which was agreed to on a Roll Call Passed -- Needed 72 of 144 to Pass -- Yeas = 142, Nays = 2",
      "date": "2025-05-06",
      "organization_id": "~{\"classification\": \"lower\"}",
      "classification": [],
      "related_entities": [],
      "_processing": {
        "log_file_created": "2025-11-26T05:54:34Z"
      }
    },
    {
      "description": "Third Reading ordered",
      "date": "2025-05-06",
      "organization_id": "~{\"classification\": \"lower\"}",
      "classification": [
        "reading-3"
      ],
      "related_entities": [],
      "_processing": {
        "log_file_created": "2025-11-26T05:54:34Z"
      }
    },
    {
      "description": "Action Calendar: Third Reading",
      "date": "2025-05-07",
      "organization_id": "~{\"classification\": \"lower\"}",
      "classification": [
        "reading-3"
      ],
      "related_entities": [],
      "_processing": {
        "log_file_created": "2025-11-26T05:54:34Z"
      }
    },
    {
      "description": "Read third time and passed in concurrence with proposal of amendment",
      "date": "2025-05-07",
      "organization_id": "~{\"classification\": \"lower\"}",
      "classification": [
        "amendment-introduction",
        "reading-3"
      ],
      "related_entities": [],
      "_processing": {
        "log_file_created": "2025-11-26T05:54:34Z"
      }
    },
    {
      "description": "House message: House passed bill in concurrence with proposal(s) of amendment",
      "date": "2025-05-08",
      "organization_id": "~{\"classification\": \"upper\"}",
      "classification": [],
      "related_entities": [],
      "_processing": {
        "log_file_created": "2025-11-26T05:54:34Z"
      }
    },
    {
      "description": "Entered on Notice Calendar",
      "date": "2025-05-09",
      "organization_id": "~{\"classification\": \"upper\"}",
      "classification": [],
      "related_entities": [],
      "_processing": {
        "log_file_created": "2025-11-26T05:54:34Z"
      }
    },
    {
      "description": "House proposal of amendment",
      "date": "2025-05-09",
      "organization_id": "~{\"classification\": \"upper\"}",
      "classification": [
        "amendment-introduction"
      ],
      "related_entities": [],
      "_processing": {
        "log_file_created": "2025-11-26T05:54:34Z"
      }
    },
    {
      "description": "Rules suspended & taken up for immediate consideration, on motion of Senator Baruth",
      "date": "2025-05-09",
      "organization_id": "~{\"classification\": \"upper\"}",
      "classification": [],
      "related_entities": [],
      "_processing": {
        "log_file_created": "2025-11-26T05:54:34Z"
      }
    },
    {
      "description": "House proposal of amendment; text",
      "date": "2025-05-09",
      "organization_id": "~{\"classification\": \"upper\"}",
      "classification": [
        "amendment-introduction"
      ],
      "related_entities": [],
      "_processing": {
        "log_file_created": "2025-11-26T05:54:34Z"
      }
    },
    {
      "description": "House proposal of amendment not concurred in; Committee of Conference requested, on motion of Senator Cummings",
      "date": "2025-05-09",
      "organization_id": "~{\"classification\": \"upper\"}",
      "classification": [
        "amendment-introduction"
      ],
      "related_entities": [],
      "_processing": {
        "log_file_created": "2025-11-26T05:54:34Z"
      }
    },
    {
      "description": "Committee of Conference appointed: Senators Cummings, Chittenden, and Brock",
      "date": "2025-05-09",
      "organization_id": "~{\"classification\": \"upper\"}",
      "classification": [],
      "related_entities": [],
      "_processing": {
        "log_file_created": "2025-11-26T05:54:34Z"
      }
    },
    {
      "description": "Senate Message: House proposal of amendment not concurred in and Committee of Conference appointed",
      "date": "2025-05-09",
      "organization_id": "~{\"classification\": \"lower\"}",
      "classification": [
        "amendment-introduction"
      ],
      "related_entities": [],
      "_processing": {
        "log_file_created": "2025-11-26T05:54:34Z"
      }
    },
    {
      "description": "Speaker appointed Reps. Kornheiser of Brattleboro, Kimbell of Woodstock, and Canfield of Fair Haven as members of the Committee of Conference on the part of the House",
      "date": "2025-05-13",
      "organization_id": "~{\"classification\": \"lower\"}",
      "classification": [],
      "related_entities": [],
      "_processing": {
        "log_file_created": "2025-11-26T05:54:34Z"
      }
    },
    {
      "description": "House message: House appointed Conference Committee members",
      "date": "2025-05-13",
      "organization_id": "~{\"classification\": \"upper\"}",
      "classification": [],
      "related_entities": [],
      "_processing": {
        "log_file_created": "2025-11-26T05:54:34Z"
      }
    },
    {
      "description": "Rules suspended and taken up for immediate consideration, pending entry on Notice Calendar, as moved by Rep. McCoy of Poultney",
      "date": "2025-05-30",
      "organization_id": "~{\"classification\": \"lower\"}",
      "classification": [],
      "related_entities": [],
      "_processing": {
        "log_file_created": "2025-11-26T05:54:34Z"
      }
    },
    {
      "description": "Committee of Conference report adopted (Senate bill)",
      "date": "2025-05-30",
      "organization_id": "~{\"classification\": \"lower\"}",
      "classification": [
        "passage"
      ],
      "related_entities": [],
      "_processing": {
        "log_file_created": "2025-11-26T05:54:34Z"
      }
    },
    {
      "description": "Rules suspended and bill messaged forthwith to the Senate as moved by Rep. McCoy of Poultney",
      "date": "2025-05-30",
      "organization_id": "~{\"classification\": \"lower\"}",
      "classification": [],
      "related_entities": [],
      "_processing": {
        "log_file_created": "2025-11-26T05:54:34Z"
      }
    },
    {
      "description": "House message: House adopted Conference Committee report",
      "date": "2025-05-31",
      "organization_id": "~{\"classification\": \"upper\"}",
      "classification": [],
      "related_entities": [],
      "_processing": {
        "log_file_created": "2025-11-26T05:54:34Z"
      }
    },
    {
      "description": "Entered on Notice Calendar",
      "date": "2025-06-03",
      "organization_id": "~{\"classification\": \"upper\"}",
      "classification": [],
      "related_entities": [],
      "_processing": {
        "log_file_created": "2025-11-26T05:54:34Z"
      }
    },
    {
      "description": "Committee of Conference report",
      "date": "2025-06-03",
      "organization_id": "~{\"classification\": \"upper\"}",
      "classification": [],
      "related_entities": [],
      "_processing": {
        "log_file_created": "2025-11-26T05:54:34Z"
      }
    },
    {
      "description": "Committee of Conference report",
      "date": "2025-06-06",
      "organization_id": "~{\"classification\": \"upper\"}",
      "classification": [],
      "related_entities": [],
      "_processing": {
        "log_file_created": "2025-11-26T05:54:34Z"
      }
    },
    {
      "description": "Unfinished Business/Committee of Conference Report",
      "date": "2025-06-09",
      "organization_id": "~{\"classification\": \"upper\"}",
      "classification": [],
      "related_entities": [],
      "_processing": {
        "log_file_created": "2025-11-26T05:54:34Z"
      }
    },
    {
      "description": "Unfinished Business/Committee of Conference Report",
      "date": "2025-06-11",
      "organization_id": "~{\"classification\": \"upper\"}",
      "classification": [],
      "related_entities": [],
      "_processing": {
        "log_file_created": "2025-11-26T05:54:34Z"
      }
    },
    {
      "description": "Unfinished Business/Committee of Conference Report",
      "date": "2025-06-13",
      "organization_id": "~{\"classification\": \"upper\"}",
      "classification": [],
      "related_entities": [],
      "_processing": {
        "log_file_created": "2025-11-26T05:54:34Z"
      }
    },
    {
      "description": "Unfinished Business/Committee of Conference Report",
      "date": "2025-06-16",
      "organization_id": "~{\"classification\": \"upper\"}",
      "classification": [],
      "related_entities": [],
      "_processing": {
        "log_file_created": "2025-11-26T05:54:34Z"
      }
    },
    {
      "description": "Committee of Conference report submitted by Senator Cummings for Committee, text",
      "date": "2025-06-16",
      "organization_id": "~{\"classification\": \"upper\"}",
      "classification": [],
      "related_entities": [],
      "_processing": {
        "log_file_created": "2025-11-26T05:54:34Z"
      }
    },
    {
      "description": "Roll Call, Requested by Sen. Collamore",
      "date": "2025-06-16",
      "organization_id": "~{\"classification\": \"upper\"}",
      "classification": [],
      "related_entities": [],
      "_processing": {
        "log_file_created": "2025-11-26T05:54:34Z"
      }
    },
    {
      "description": "Committee of Conference report adopted on roll call Passed -- Needed 14 of 28 to Pass -- Yeas = 28, Nays = 0",
      "date": "2025-06-16",
      "organization_id": "~{\"classification\": \"upper\"}",
      "classification": [],
      "related_entities": [],
      "_processing": {
        "log_file_created": "2025-11-26T05:54:34Z"
      }
    },
    {
      "description": "Title amended",
      "date": "2025-06-16",
      "organization_id": "~{\"classification\": \"upper\"}",
      "classification": [],
      "related_entities": [],
      "_processing": {
        "log_file_created": "2025-11-26T05:54:34Z"
      }
    },
    {
      "description": "As passed by Senate and House",
      "date": "2025-06-16",
      "organization_id": "~{\"classification\": \"upper\"}",
      "classification": [
        "passage"
      ],
      "related_entities": [],
      "_processing": {
        "log_file_created": "2025-11-26T05:54:34Z"
      }
    },
    {
      "description": "Rules suspended & ordered delivered to Governor forthwith, on motion of Senator Lyons",
      "date": "2025-06-16",
      "organization_id": "~{\"classification\": \"upper\"}",
      "classification": [
        "executive-receipt"
      ],
      "related_entities": [],
      "_processing": {
        "log_file_created": "2025-11-26T05:54:34Z"
      }
    },
    {
      "description": "Senate Message: Report of Committee of Conference adopted",
      "date": "2025-06-16",
      "organization_id": "~{\"classification\": \"lower\"}",
      "classification": [],
      "related_entities": [],
      "_processing": {
        "log_file_created": "2025-11-26T05:54:34Z"
      }
    },
    {
      "description": "Delivered to Governor on June 20, 2025",
      "date": "2025-06-16",
      "organization_id": "~{\"classification\": \"upper\"}",
      "classification": [
        "executive-receipt"
      ],
      "related_entities": [],
      "_processing": {
        "log_file_created": "2025-11-26T05:54:34Z"
      }
    },
    {
      "description": "Signed by Governor on June 25, 2025",
      "date": "2025-06-16",
      "organization_id": "~{\"classification\": \"executive\"}",
      "classification": [
        "executive-signature"
      ],
      "related_entities": [],
      "_processing": {
        "log_file_created": "2025-11-26T05:54:34Z"
      }
    },
    {
      "description": "Senate Message: Signed by Governor June 25, 2025",
      "date": "2025-06-16",
      "organization_id": "~{\"classification\": \"executive\"}",
      "classification": [
        "executive-signature"
      ],
      "related_entities": [],
      "_processing": {
        "log_file_created": "2025-11-26T05:54:34Z"
      }
    }
  ],
  "sponsorships": [
    {
      "name": "Ruth Hardy",
      "classification": "primary",
      "entity_type": "person",
      "primary": true,
      "person_id": "~{\"chamber\": \"upper\", \"name\": \"Ruth Hardy\"}",
      "organization_id": null
    },
    {
      "name": "Alison Clarkson",
      "classification": "cosponsor",
      "entity_type": "person",
      "primary": false,
      "person_id": "~{\"chamber\": \"upper\", \"name\": \"Alison Clarkson\"}",
      "organization_id": null
    },
    {
      "name": "Martine Gulick",
      "classification": "cosponsor",
      "entity_type": "person",
      "primary": false,
      "person_id": "~{\"chamber\": \"upper\", \"name\": \"Martine Gulick\"}",
      "organization_id": null
    },
    {
      "name": "Wendy Harrison",
      "classification": "cosponsor",
      "entity_type": "person",
      "primary": false,
      "person_id": "~{\"chamber\": \"upper\", \"name\": \"Wendy Harrison\"}",
      "organization_id": null
    },
    {
      "name": "Joseph Major",
      "classification": "cosponsor",
      "entity_type": "person",
      "primary": false,
      "person_id": "~{\"chamber\": \"upper\", \"name\": \"Joseph Major\"}",
      "organization_id": null
    },
    {
      "name": "Robert Norris",
      "classification": "cosponsor",
      "entity_type": "person",
      "primary": false,
      "person_id": "~{\"chamber\": \"upper\", \"name\": \"Robert Norris\"}",
      "organization_id": null
    },
    {
      "name": "Tanya Vyhovsky",
      "classification": "cosponsor",
      "entity_type": "person",
      "primary": false,
      "person_id": "~{\"chamber\": \"upper\", \"name\": \"Tanya Vyhovsky\"}",
      "organization_id": null
    },
    {
      "name": "David Weeks",
      "classification": "cosponsor",
      "entity_type": "person",
      "primary": false,
      "person_id": "~{\"chamber\": \"upper\", \"name\": \"David Weeks\"}",
      "organization_id": null
    },
    {
      "name": "Rebecca White",
      "classification": "cosponsor",
      "entity_type": "person",
      "primary": false,
      "person_id": "~{\"chamber\": \"upper\", \"name\": \"Rebecca White\"}",
      "organization_id": null
    }
  ],
  "related_bills": [],
  "versions": [
    {
      "note": "As Introduced",
      "links": [
        {
          "url": "https://legislature.vermont.gov/Documents/2026/Docs/BILLS/S-0051/S-0051%20As%20Introduced.pdf",
          "media_type": "application/pdf"
        }
      ],
      "date": "",
      "classification": ""
    },
    {
      "note": "As Passed By the Senate (Official)",
      "links": [
        {
          "url": "https://legislature.vermont.gov/Documents/2026/Docs/BILLS/S-0051/S-0051%20As%20passed%20by%20the%20Senate%20Official.pdf",
          "media_type": "application/pdf"
        }
      ],
      "date": "",
      "classification": ""
    },
    {
      "note": "As Passed By the Senate (Unofficial)",
      "links": [
        {
          "url": "https://legislature.vermont.gov/Documents/2026/Docs/BILLS/S-0051/S-0051%20As%20Passed%20by%20the%20Senate%20Unofficial.pdf",
          "media_type": "application/pdf"
        }
      ],
      "date": "",
      "classification": ""
    },
    {
      "note": "House Proposal of Amendment (Official)",
      "links": [
        {
          "url": "https://legislature.vermont.gov/Documents/2026/Docs/BILLS/S-0051/S-0051%20House%20proposal%20of%20amendment%20Official.pdf",
          "media_type": "application/pdf"
        }
      ],
      "date": "",
      "classification": ""
    },
    {
      "note": "House Proposal of Amendment (Unofficial)",
      "links": [
        {
          "url": "https://legislature.vermont.gov/Documents/2026/Docs/BILLS/S-0051/S-0051%20House%20Proposal%20of%20Amendment%20Unofficial.pdf",
          "media_type": "application/pdf"
        }
      ],
      "date": "",
      "classification": ""
    },
    {
      "note": "As Passed by Both House and Senate (Official)",
      "links": [
        {
          "url": "https://legislature.vermont.gov/Documents/2026/Docs/BILLS/S-0051/S-0051%20As%20Passed%20by%20Both%20House%20and%20Senate%20Official.pdf",
          "media_type": "application/pdf"
        }
      ],
      "date": "",
      "classification": ""
    },
    {
      "note": "As Passed by Both House and Senate (Unofficial)",
      "links": [
        {
          "url": "https://legislature.vermont.gov/Documents/2026/Docs/BILLS/S-0051/S-0051%20As%20Passed%20by%20Both%20House%20and%20Senate%20Unofficial.pdf",
          "media_type": "application/pdf"
        }
      ],
      "date": "",
      "classification": ""
    },
    {
      "note": "As Enacted",
      "links": [
        {
          "url": "https://legislature.vermont.gov/Documents/2026/Docs/ACTS/ACT071/ACT071%20As%20Enacted.pdf",
          "media_type": "application/pdf"
        }
      ],
      "date": "",
      "classification": ""
    },
    {
      "note": "Act Summary",
      "links": [
        {
          "url": "https://legislature.vermont.gov/Documents/2026/Docs/ACTS/ACT071/ACT071%20Act%20Summary.pdf",
          "media_type": "application/pdf"
        }
      ],
      "date": "",
      "classification": ""
    }
  ],
  "documents": [
    {
      "note": "Witness List",
      "links": [
        {
          "url": "https://legislature.vermont.gov/bill/print/2026/S51/witnesses",
          "media_type": "text/html"
        }
      ],
      "date": "",
      "classification": ""
    },
    {
      "note": "Conference Committee Members",
      "links": [
        {
          "url": "https://legislature.vermont.gov/bill/print/2026/S51/conference",
          "media_type": "text/html"
        }
      ],
      "date": "",
      "classification": ""
    },
    {
      "note": "Committee Meetings",
      "links": [
        {
          "url": "https://legislature.vermont.gov/bill/print/2026/S51/meetings",
          "media_type": "text/html"
        }
      ],
      "date": "",
      "classification": ""
    }
  ],
  "citations": [],
  "sources": [
    {
      "url": "http://legislature.vermont.gov/bill/loadBillsIntroduced/2026/",
      "note": ""
    },
    {
      "url": "http://legislature.vermont.gov/bill/status/2026/S.51",
      "note": ""
    },
    {
      "url": "http://legislature.vermont.gov/bill/loadBillDetailedStatus/2026/643",
      "note": ""
    },
    {
      "url": "http://legislature.vermont.gov/bill/loadBillRollCalls/2026/643",
      "note": ""
    }
  ],
  "extras": {},
  "jurisdiction": {
    "id": "ocd-jurisdiction/country:us/state:vt/government",
    "name": "Vermont",
    "classification": "state",
    "division_id": "ocd-division/country:us/state:vt"
  },
  "_processing": {
    "logs_latest_update": "2025-11-26T05:54:35Z"
  }
}